MANIFEST.in
Procfile
development.ini
initialize_db.py
newdevelopment.ini
production.ini
runprocessor.py
runweb.py
setup.py
osmhm_site/__init__.py
osmhm_site/models.py
osmhm_site/security.py
osmhm_site/subscribers.py
osmhm_site/tests.py
osmhm_site.egg-info/PKG-INFO
osmhm_site.egg-info/SOURCES.txt
osmhm_site.egg-info/dependency_links.txt
osmhm_site.egg-info/entry_points.txt
osmhm_site.egg-info/not-zip-safe
osmhm_site.egg-info/requires.txt
osmhm_site.egg-info/top_level.txt
osmhm_site/scripts/__init__.py
osmhm_site/scripts/initializedb.py
osmhm_site/static/pyramid-16x16.png
osmhm_site/static/pyramid.png
osmhm_site/static/theme.css
osmhm_site/static/theme.min.css
osmhm_site/static/css/dashboard.css
osmhm_site/static/js/jquery-1.11.3.min.js
osmhm_site/static/twbs/css/bootstrap-theme.css
osmhm_site/static/twbs/css/bootstrap-theme.min.css
osmhm_site/static/twbs/css/bootstrap.css
osmhm_site/static/twbs/css/bootstrap.min.css
osmhm_site/static/twbs/js/bootstrap.js
osmhm_site/static/twbs/js/bootstrap.min.js
osmhm_site/static/twbs/js/npm.js
osmhm_site/templates/admin.mako
osmhm_site/templates/admin_user_list.mako
osmhm_site/templates/admin_whitelist_add.mako
osmhm_site/templates/base.mako
osmhm_site/templates/history.mako
osmhm_site/templates/home.mako
osmhm_site/templates/key_watch.mako
osmhm_site/templates/key_watch_list.mako
osmhm_site/templates/key_watch_list_add.mako
osmhm_site/templates/object_watch.mako
osmhm_site/templates/object_watch_list.mako
osmhm_site/templates/object_watch_list_add.mako
osmhm_site/templates/user_watch.mako
osmhm_site/templates/user_watch_list.mako
osmhm_site/templates/user_watch_list_add.mako
osmhm_site/templates/watch.mako
osmhm_site/templates/watch_whitelist.mako
osmhm_site/views/__init__.py
osmhm_site/views/admin.py
osmhm_site/views/history.py
osmhm_site/views/key_watch.py
osmhm_site/views/object_watch.py
osmhm_site/views/security.py
osmhm_site/views/user_watch.py
osmhm_site/views/views.py
osmhm_site/views/watch.py